pyiron_experimental/__init__.py
pyiron_experimental/_version.py
pyiron_experimental/image_proc.py
pyiron_experimental/matchseries.py
pyiron_experimental/tem_analysis.py
pyiron_experimental-0.0.3.dist-info/LICENSE
pyiron_experimental-0.0.3.dist-info/METADATA
pyiron_experimental-0.0.3.dist-info/WHEEL
pyiron_experimental-0.0.3.dist-info/top_level.txt
pyiron_experimental-0.0.3.dist-info/RECORD
