Metadata-Version: 2.1
Name: pyiron-experimental
Version: 0.0.3
Summary: Repository for experimental plugins to the pyiron IDE.
Home-page: https://github.com/pyiron/pyiron_experimental
Author: Max-Planck-Institut für Eisenforschung GmbH - Computational Materials Design (CM) Department
Author-email: hassani@mpie.de
License: BSD
Keywords: pyiron
Classifier: Development Status :: 4 - Beta
Classifier: Topic :: Scientific/Engineering :: Physics
Classifier: License :: OSI Approved :: BSD License
Classifier: Intended Audience :: Science/Research
Classifier: Operating System :: OS Independent
Classifier: Programming Language :: Python :: 3
Classifier: Programming Language :: Python :: 3.9
Classifier: Programming Language :: Python :: 3.10
License-File: LICENSE
Requires-Dist: pyiron-base >=0.6.6
Requires-Dist: matplotlib >=3.8.1
Requires-Dist: pystem >=0.0.26
Requires-Dist: hyperspy >=1.7.5
Requires-Dist: scanf >=1.5.2
